MANIFEST.in
README.rst
setup.py
mqtt_wrapper/__init__.py
mqtt_wrapper/bridge.py
mqtt_wrapper.egg-info/PKG-INFO
mqtt_wrapper.egg-info/SOURCES.txt
mqtt_wrapper.egg-info/dependency_links.txt
mqtt_wrapper.egg-info/not-zip-safe
mqtt_wrapper.egg-info/requires.txt
mqtt_wrapper.egg-info/top_level.txt