Metadata-Version: 1.0
Name: mqtt-wrapper
Version: 0.4
Summary: wrapper for paho mqtt client
Home-page: https://github.com/EmaroLab/mqtt_wrapper.git
Author: Alessandro Carfi
Author-email: carfi.alessandro@gmail.com
License: MIT
Platform: UNKNOWN
